bluehive/__init__.py
bluehive/_base_client.py
bluehive/_client.py
bluehive/_compat.py
bluehive/_constants.py
bluehive/_exceptions.py
bluehive/_files.py
bluehive/_models.py
bluehive/_qs.py
bluehive/_resource.py
bluehive/_response.py
bluehive/_streaming.py
bluehive/_types.py
bluehive/_version.py
bluehive/py.typed
bluehive/_utils/__init__.py
bluehive/_utils/_compat.py
bluehive/_utils/_datetime_parse.py
bluehive/_utils/_json.py
bluehive/_utils/_logs.py
bluehive/_utils/_proxy.py
bluehive/_utils/_reflection.py
bluehive/_utils/_resources_proxy.py
bluehive/_utils/_streams.py
bluehive/_utils/_sync.py
bluehive/_utils/_transform.py
bluehive/_utils/_typing.py
bluehive/_utils/_utils.py
bluehive/lib/.keep
bluehive/resources/__init__.py
bluehive/resources/database.py
bluehive/resources/employees.py
bluehive/resources/fax.py
bluehive/resources/health.py
bluehive/resources/hl7.py
bluehive/resources/integrations.py
bluehive/resources/orders.py
bluehive/resources/providers.py
bluehive/resources/version.py
bluehive/resources/employers/__init__.py
bluehive/resources/employers/employers.py
bluehive/resources/employers/service_bundles.py
bluehive/types/__init__.py
bluehive/types/database_check_health_response.py
bluehive/types/employee_create_params.py
bluehive/types/employee_create_response.py
bluehive/types/employee_delete_response.py
bluehive/types/employee_link_user_params.py
bluehive/types/employee_link_user_response.py
bluehive/types/employee_list_params.py
bluehive/types/employee_list_response.py
bluehive/types/employee_retrieve_response.py
bluehive/types/employee_unlink_user_params.py
bluehive/types/employee_unlink_user_response.py
bluehive/types/employee_update_params.py
bluehive/types/employee_update_response.py
bluehive/types/employer_create_params.py
bluehive/types/employer_create_response.py
bluehive/types/employer_list_response.py
bluehive/types/employer_retrieve_response.py
bluehive/types/fax_list_providers_response.py
bluehive/types/fax_retrieve_status_response.py
bluehive-0.1.0a24.dist-info/METADATA
bluehive-0.1.0a24.dist-info/WHEEL
bluehive-0.1.0a24.dist-info/licenses/LICENSE
bluehive-0.1.0a24.dist-info/RECORD
